MemoryZeroController/memoryzero.sv
module Memory64x8(clock, addr, din, we, dout);
parameter ADDRWIDTH = 0;
parameter DATAWIDTH = 0;

input clock;
input [ADDRWIDTH-1:0] addr;
input [DATAWIDTH-1:0] din;
input we;
output [DATAWIDTH-1:0] dout;

reg [DATAWIDTH-1:0] m [(1 << ADDRWIDTH)-1:0];

assign dout = m[addr];

always @(posedge clock)
	if (we) m[addr] <= din;
endmodule

// Latch
module Register(load, din, dout);
parameter WIDTH = 0;
input load;
input [WIDTH-1:0] din;
output [WIDTH-1:0] dout;

reg [WIDTH-1:0] m;

assign dout = m;
always_latch
	if (load) m <= din;
endmodule

module UpCounter(clock, din, load, enable, dout);
parameter WIDTH = 0;
input clock;
input [WIDTH-1:0] din;
input load;
input enable;
output [WIDTH-1:0] dout;

reg [WIDTH-1:0] m;

assign dout = m;
always_ff @(posedge clock)
	begin
	if (load)
		m <= din;
	else if (enable)
		m <= m + 1'b1;
	else
		m <= m;
	end
endmodule

module Mux2x1(d1, d0, select, dout);
parameter WIDTH = 0;
input [WIDTH-1:0] d1, d0;
input select;
output [WIDTH-1:0] dout;

assign dout = select ? d1 : d0;
endmodule

module JKFF(clock, j, k, q);
input clock;
input j, k;
output q;

reg q;

always_ff @(posedge clock)
	begin
	if ({j,k} == 2'b11)
		q <= ~q;
	else if ({j,k} == 2'b10)
		q <= 1;
	else if ({j,k} == 2'b01)
		q <= '0;
	else
		q <= q;
	end
endmodule

module Comparator(dina, dinb, aEQb);
parameter WIDTH = 0;
input [WIDTH-1:0] dina, dinb;
output aEQb;

assign aEQb = (dina == dinb);
endmodule

module DataPath(clock, ld_high, ld_low, addr, din, write, set_busy, clr_busy, ld_cnt, cnt_en, addr_sel, zero_we, cnt_eq, dout, busy);
parameter ADDRWIDTH = 0;
parameter DATAWIDTH = 0;

input clock;
input ld_high, ld_low;
input [ADDRWIDTH-1:0] addr;
input [DATAWIDTH-1:0] din;
input write;
input set_busy, clr_busy, ld_cnt, cnt_en, addr_sel, zero_we;
output cnt_eq;

output [DATAWIDTH-1:0] dout;
output busy;

wire [ADDRWIDTH-1:0] dina, dinb, dcnt;
wire [ADDRWIDTH-1:0] addrm;
wire [DATAWIDTH-1:0] dinm;
wire busy_ff;
wire mem_we;

Register #(ADDRWIDTH) R1 (ld_high,  addr, dina);
Register #(ADDRWIDTH) R2 (ld_low,	addr, dcnt);

UpCounter #(ADDRWIDTH) UC (clock, dcnt, ld_cnt, cnt_en, dinb);
JKFF BusyFF (clock, set_busy, clr_busy, busy_ff);
assign busy = busy_ff | set_busy;

Mux2x1 #(ADDRWIDTH) AddrMux(dinb, addr, addr_sel, addrm);
Mux2x1 #(DATAWIDTH) DataMux('0,    din, addr_sel, dinm);

Comparator #(ADDRWIDTH) C (dina, dinb, cnt_eq);

assign mem_we = zero_we | (write & !busy);
Memory64x8 #(ADDRWIDTH, DATAWIDTH) Mem (clock, addrm, dinm, mem_we, dout);

endmodule

module MemoryZeroController(clock, reset, zero, cnt_eq, set_busy, clr_busy, ld_cnt, cnt_en, addr_sel, zero_we);
input clock, reset;
input zero;
input cnt_eq;
output set_busy;
output clr_busy;
output ld_cnt;
output cnt_en;
output addr_sel;
output zero_we;

reg set_busy, clr_busy, ld_cnt, cnt_en, addr_sel, zero_we;

enum logic [1:0] {Init, Load, Write} State, NextState;


// Sequential block: reset and update state register
always_ff @(posedge clock)
begin
if (reset)
	State <= Init;
else
	State <= NextState;
end


// Output logic
always_comb
begin
{set_busy, clr_busy, ld_cnt, cnt_en, addr_sel, zero_we} = '0;
if (reset)
	clr_busy = '1;
else
	case (State)
		Init:
			begin
			if (zero)
				set_busy = '1;
			else
				clr_busy = '1;
			end
		
		Load:
			begin
			set_busy = '1;
			ld_cnt = '1;
			end

		Write:
			begin
			zero_we = '1;
			set_busy = '1;
			cnt_en = '1;
			addr_sel = '1;
			end
	endcase
end

// Next state logic
always_comb
begin
NextState = State;
case (State)
	Init:
		if (zero)
			NextState = Load;
			
	Load:
		NextState = Write;
		
	Write:
		if (cnt_eq)
			NextState = Init;
endcase
end
endmodule

module mz(clock, reset, ld_high, addr, ld_low, din, write, zero, dout, busy);

parameter ADDRWIDTH = 8;
parameter DATAWIDTH = 8;

input clock;
input reset;
input ld_high, ld_low;
input [ADDRWIDTH-1:0] addr;
input [DATAWIDTH-1:0] din;
input write;
input zero;
output [DATAWIDTH-1:0] dout;
output busy;

wire set_busy, clr_busy, ld_cnt, cnt_en, addr_sel, zero_we, cnt_eq;

DataPath #(ADDRWIDTH, DATAWIDTH) DP(clock, ld_high, ld_low, addr, din, write, set_busy, clr_busy, ld_cnt, cnt_en, addr_sel, zero_we, cnt_eq, dout, busy);
MemoryZeroController FSM(clock, reset, zero, cnt_eq, set_busy, clr_busy, ld_cnt, cnt_en, addr_sel, zero_we);
endmodule

MemoryZeroController/fsmtb.sv
module top;

    parameter ADDRWIDTH = 8;
    parameter DATAWIDTH = 8;
    parameter CLOCK_PERIOD_NS = 10; // Clock period in nanoseconds, 100MHz

    reg clock;
    reg reset;
    reg ld_high, ld_low;
    reg [ADDRWIDTH-1:0] addr;
    reg [DATAWIDTH-1:0] din;
    reg write;
    reg zero;
    wire [DATAWIDTH-1:0] dout;
    wire busy;

    // Instantiate the mz module
    mz #(ADDRWIDTH, DATAWIDTH) DUT (
        .clock(clock),
        .reset(reset),
        .ld_high(ld_high),
        .ld_low(ld_low),
        .addr(addr),
        .din(din),
        .write(write),
        .zero(zero),
        .dout(dout),
        .busy(busy)
    );

    // Clock generation
    always #(CLOCK_PERIOD_NS / 2) clock = ~clock; // Generate clock with defined period

    // Helper task to wait for a number of clock cycles
    task wait_clock_cycles(input integer cycles);
        integer i;
        for (i = 0; i < cycles; i++) begin
            @(posedge clock);
        end
    endtask

    // Test sequence
    initial begin
        // Initialize inputs
        clock = 0;
        reset = 1;
        ld_high = 0;
        ld_low = 0;
        addr = 0;
        din = 0;
        write = 0;
        zero = 0;

        // Apply reset
        wait_clock_cycles(2);
        reset = 0;
        wait_clock_cycles(1);

        // Test Case 1: Write a value to a specific address
        @(negedge clock);
        addr = 8'hAA;
        din = 8'h55;
        write = 1;
        @(posedge clock);
        write = 0;
        wait_clock_cycles(1);
        if (dout !== 8'h55) $display("Test Case 1 Failed: Memory write error at address %h", addr);
        else $display("Test Case 1 Passed");

        // Test Case 2: Zero out a range of memory
        @(negedge clock);
        ld_high = 1; addr = 8'hFF; // Set high address for zeroing
        @(posedge clock);
        ld_high = 0;
        @(negedge clock);
        ld_low = 1; addr = 8'h00; // Set low address for zeroing
        @(posedge clock);
        ld_low = 0;
        @(negedge clock);
        zero = 1;
        @(posedge clock);
        zero = 0;
        wait_clock_cycles(100); // Wait for zeroing to complete
        @(negedge clock);
        addr = 8'h00;
        wait_clock_cycles(10);
        if (dout !== 8'h00) $display("Test Case 2 Failed: Memory zero error at address %h", addr);
        else $display("Test Case 2 Passed");

        // Test Case 3: Write and then zero out a range including the written address
        @(negedge clock);
        addr = 8'h55;
        din = 8'hAA;
        write = 1;
        @(posedge clock);
        write = 0;
        @(negedge clock);
        ld_high = 1; addr = 8'hFF;
        @(posedge clock);
        ld_high = 0;
        @(negedge clock);
        ld_low = 1; addr = 8'h00;
        @(posedge clock);
        ld_low = 0;
        @(negedge clock);
        zero = 1;
        @(posedge clock);
        zero = 0;
        wait_clock_cycles(100); // Wait for zeroing to complete
        @(negedge clock);
        addr = 8'h55;
        wait_clock_cycles(10);
        if (dout !== 8'h00) $display("Test Case 3 Failed: Memory zero error at address %h", addr);
        else $display("Test Case 3 Passed");

        // Test Case 4: Attempt to write while zeroing is in progress
        @(negedge clock);
        ld_high = 1; addr = 8'hFF;
        @(posedge clock);
        ld_high = 0;
        @(negedge clock);
        ld_low = 1; addr = 8'h00;
        @(posedge clock);
        ld_low = 0;
        @(negedge clock);
        zero = 1;
        @(posedge clock);
        addr = 8'h33;
        din = 8'h77;
        write = 1;
        wait_clock_cycles(1);
        write = 0;
        zero = 0;
        @(negedge clock);
        addr = 8'h33;
        wait_clock_cycles(10);
        if (dout === 8'h77) $display("Test Case 4 Failed: Write operation should not occur during zeroing");
        else $display("Test Case 4 Passed");

        // Test Case 5: Zero out a single address by setting high and low addresses the same
        @(negedge clock);
        ld_high = 1; addr = 8'hAA;
        @(posedge clock);
        ld_high = 0;
        @(negedge clock);
        ld_low = 1; addr = 8'hAA;
        @(posedge clock);
        ld_low = 0;
        @(negedge clock);
        zero = 1;
        @(posedge clock);
        zero = 0;
        wait_clock_cycles(100); // Wait for zeroing to complete
        @(negedge clock);
        addr = 8'hAA;
        wait_clock_cycles(10);
        if (dout !== 8'h00) $display("Test Case 5 Failed: Memory zero error at single address %h", addr);
        else $display("Test Case 5 Passed");

        // Test Case 6: Check busy flag behavior during zeroing
        @(negedge clock);
        ld_high = 1; addr = 8'hFF;
        @(posedge clock);
        ld_high = 0;
        @(negedge clock);
        ld_low = 1; addr = 8'h00;
        @(posedge clock);
        ld_low = 0;
        @(negedge clock);
        zero = 1;
        wait_clock_cycles(1);
        if (!busy) $display("Test Case 6 Failed: Busy flag not set during zeroing");
        @(posedge clock);
        zero = 0;
        wait_clock_cycles(100); // Wait for zeroing to complete
        if (busy) $display("Test Case 6 Failed: Busy flag not cleared after zeroing");
        else $display("Test Case 6 Passed");

        // Test Case 7: Normal mode operation after zero mode
        @(negedge clock);
        ld_high = 1; addr = 8'hFF;
        @(posedge clock);
        ld_high = 0;
        @(negedge clock);
        ld_low = 1; addr = 8'h00;
        @(posedge clock);
        ld_low = 0;
        @(negedge clock);
        zero = 1;
        @(posedge clock);
        zero = 0;
        wait_clock_cycles(100); // Wait for zeroing to complete
        @(negedge clock);
        addr = 8'hAA;
        din = 8'hBB;
        write = 1;
        @(posedge clock);
        write = 0;
        wait_clock_cycles(1);
        if (dout !== 8'hBB) $display("Test Case 7 Failed: Normal mode write error after zero mode");
        else $display("Test Case 7 Passed");

        // Finish the simulation
        wait_clock_cycles(10);
        $finish;
    end

endmodule

MemoryZeroController/memoryzero_waveforms.vcd
$date
	Sat May 23 21:28:00 2026
$end
$version
	QuestaSim Version 2021.3_1
$end
$timescale
	1ns
$end

$scope module top $end
$var reg 1 ! clock $end
$var reg 1 " reset $end
$var reg 1 # ld_high $end
$var reg 1 $ ld_low $end
$var reg 8 % addr [7:0] $end
$var reg 8 & din [7:0] $end
$var reg 1 ' write $end
$var reg 1 ( zero $end
$var wire 1 ) dout [7] $end
$var wire 1 * dout [6] $end
$var wire 1 + dout [5] $end
$var wire 1 , dout [4] $end
$var wire 1 - dout [3] $end
$var wire 1 . dout [2] $end
$var wire 1 / dout [1] $end
$var wire 1 0 dout [0] $end
$var wire 1 1 busy $end

$scope module DUT $end
$var wire 1 2 set_busy $end
$var wire 1 3 clr_busy $end
$var wire 1 4 ld_cnt $end
$var wire 1 5 cnt_en $end
$var wire 1 6 addr_sel $end
$var wire 1 7 zero_we $end
$var wire 1 8 cnt_eq $end

$scope module FSM $end
$var reg 2 9 State [1:0] $end
$var reg 2 : NextState [1:0] $end
$upscope $end

$scope module DP $end
$var wire 1 ; dina [7] $end
$var wire 1 < dina [6] $end
$var wire 1 = dina [5] $end
$var wire 1 > dina [4] $end
$var wire 1 ? dina [3] $end
$var wire 1 @ dina [2] $end
$var wire 1 A dina [1] $end
$var wire 1 B dina [0] $end
$var wire 1 C dcnt [7] $end
$var wire 1 D dcnt [6] $end
$var wire 1 E dcnt [5] $end
$var wire 1 F dcnt [4] $end
$var wire 1 G dcnt [3] $end
$var wire 1 H dcnt [2] $end
$var wire 1 I dcnt [1] $end
$var wire 1 J dcnt [0] $end
$var wire 1 K dinb [7] $end
$var wire 1 L dinb [6] $end
$var wire 1 M dinb [5] $end
$var wire 1 N dinb [4] $end
$var wire 1 O dinb [3] $end
$var wire 1 P dinb [2] $end
$var wire 1 Q dinb [1] $end
$var wire 1 R dinb [0] $end
$var wire 1 S addrm [7] $end
$var wire 1 T addrm [6] $end
$var wire 1 U addrm [5] $end
$var wire 1 V addrm [4] $end
$var wire 1 W addrm [3] $end
$var wire 1 X addrm [2] $end
$var wire 1 Y addrm [1] $end
$var wire 1 Z addrm [0] $end
$var wire 1 [ dinm [7] $end
$var wire 1 \ dinm [6] $end
$var wire 1 ] dinm [5] $end
$var wire 1 ^ dinm [4] $end
$var wire 1 _ dinm [3] $end
$var wire 1 ` dinm [2] $end
$var wire 1 a dinm [1] $end
$var wire 1 b dinm [0] $end
$var wire 1 c mem_we $end
$upscope $end
$upscope $end
$upscope $end
$enddefinitions $end
#0
$dumpvars
0!
1"
0#
0$
b0 %
b0 &
0'
0(
bx 9
bx :
x0
x/
x.
x-
x,
x+
x*
x)
x1
02
13
04
05
06
07
x8
xB
xA
x@
x?
x>
x=
x<
x;
xR
xQ
xP
xO
xN
xM
xL
xK
xJ
xI
xH
xG
xF
xE
xD
xC
0Z
0Y
0X
0W
0V
0U
0T
0S
0b
0a
0`
0_
0^
0]
0\
0[
0c
$end
#5
1!
b0 9
01
b0 :
#10
0!
#15
1!
0"
#20
0!
#25
1!
#30
0!
b10101010 %
b1010101 &
1'
1b
1`
1^
1\
1c
1Y
1W
1U
1S
#35
1!
0'
0c
10
0/
1.
0-
1,
0+
1*
0)
#40
0!
#45
1!
#50
0!
1#
b11111111 %
1Z
1X
1V
1T
x0
x/
x.
x-
x,
x+
x*
x)
1B
1A
1@
1?
1>
1=
1<
1;
#55
1!
0#
#60
0!
1$
b0 %
0Z
0Y
0X
0W
0V
0U
0T
0S
0J
0I
0H
0G
0F
0E
0D
0C
#65
1!
0$
#70
0!
1(
b1 :
03
12
11
#75
1!
0(
b0 :
02
13
01
b1 9
11
b1 :
b10 :
03
12
14
#80
0!
#85
1!
b10 9
0R
0Q
0P
0O
0N
0M
0L
0K
08
04
17
15
16
1c
0b
0`
0^
0\
#90
0!
#95
1!
1R
00
0/
0.
0-
0,
0+
0*
0)
1Z
x0
x/
x.
x-
x,
x+
x*
x)
#100
0!
#105
1!
00
0/
0.
0-
0,
0+
0*
0)
0R
1Q
0Z
1Y
x0
x/
x.
x-
x,
x+
x*
x)
#110
0!
#115
1!
1R
00
0/
0.
0-
0,
0+
0*
0)
1Z
x0
x/
x.
x-
x,
x+
x*
x)
#120
0!
#125
1!
00
0/
0.
0-
0,
0+
0*
0)
0R
0Q
1P
0Z
0Y
1X
x0
x/
x.
x-
x,
x+
x*
x)
#130
0!
#135
1!
1R
00
0/
0.
0-
0,
0+
0*
0)
1Z
x0
x/
x.
x-
x,
x+
x*
x)
#140
0!
#145
1!
00
0/
0.
0-
0,
0+
0*
0)
0R
1Q
0Z
1Y
x0
x/
x.
x-
x,
x+
x*
x)
#150
0!
#155
1!
1R
00
0/
0.
0-
0,
0+
0*
0)
1Z
x0
x/
x.
x-
x,
x+
x*
x)
#160
0!
#165
1!
00
0/
0.
0-
0,
0+
0*
0)
0R
0Q
0P
1O
0Z
0Y
0X
1W
x0
x/
x.
x-
x,
x+
x*
x)
#170
0!
#175
1!
1R
00
0/
0.
0-
0,
0+
0*
0)
1Z
x0
x/
x.
x-
x,
x+
x*
x)
#180
0!
b1010101 %
b10101010 &
1'
#185
1!
0'
00
0/
0.
0-
0,
0+
0*
0)
0R
1Q
0Z
1Y
x0
x/
x.
x-
x,
x+
x*
x)
#190
0!
1#
b11111111 %
#195
1!
0#
1R
00
0/
0.
0-
0,
0+
0*
0)
1Z
x0
x/
x.
x-
x,
x+
x*
x)
#200
0!
1$
b0 %
#205
1!
0$
00
0/
0.
0-
0,
0+
0*
0)
0R
0Q
1P
0Z
0Y
1X
x0
x/
x.
x-
x,
x+
x*
x)
#210
0!
1(
#215
1!
0(
1R
00
0/
0.
0-
0,
0+
0*
0)
1Z
x0
x/
x.
x-
x,
x+
x*
x)
#220
0!
#225
1!
00
0/
0.
0-
0,
0+
0*
0)
0R
1Q
0Z
1Y
x0
x/
x.
x-
x,
x+
x*
x)
#230
0!
#235
1!
1R
00
0/
0.
0-
0,
0+
0*
0)
1Z
x0
x/
x.
x-
x,
x+
x*
x)
#240
0!
#245
1!
00
0/
0.
0-
0,
0+
0*
0)
0R
0Q
0P
0O
1N
0Z
0Y
0X
0W
1V
x0
x/
x.
x-
x,
x+
x*
x)
#250
0!
#255
1!
1R
00
0/
0.
0-
0,
0+
0*
0)
1Z
x0
x/
x.
x-
x,
x+
x*
x)
#260
0!
#265
1!
00
0/
0.
0-
0,
0+
0*
0)
0R
1Q
0Z
1Y
x0
x/
x.
x-
x,
x+
x*
x)
#270
0!
#275
1!
1R
00
0/
0.
0-
0,
0+
0*
0)
1Z
x0
x/
x.
x-
x,
x+
x*
x)
#280
0!
#285
1!
00
0/
0.
0-
0,
0+
0*
0)
0R
0Q
1P
0Z
0Y
1X
x0
x/
x.
x-
x,
x+
x*
x)
#290
0!
#295
1!
1R
00
0/
0.
0-
0,
0+
0*
0)
1Z
x0
x/
x.
x-
x,
x+
x*
x)
#300
0!
#305
1!
00
0/
0.
0-
0,
0+
0*
0)
0R
1Q
0Z
1Y
x0
x/
x.
x-
x,
x+
x*
x)
#310
0!
#315
1!
1R
00
0/
0.
0-
0,
0+
0*
0)
1Z
x0
x/
x.
x-
x,
x+
x*
x)
#320
0!
#325
1!
00
0/
0.
0-
0,
0+
0*
0)
0R
0Q
0P
1O
0Z
0Y
0X
1W
x0
x/
x.
x-
x,
x+
x*
x)
#330
0!
#335
1!
1R
00
0/
0.
0-
0,
0+
0*
0)
1Z
x0
x/
x.
x-
x,
x+
x*
x)
#340
0!
#345
1!
00
0/
0.
0-
0,
0+
0*
0)
0R
1Q
0Z
1Y
x0
x/
x.
x-
x,
x+
x*
x)
#350
0!
#355
1!
1R
00
0/
0.
0-
0,
0+
0*
0)
1Z
x0
x/
x.
x-
x,
x+
x*
x)
#360
0!
#365
1!
00
0/
0.
0-
0,
0+
0*
0)
0R
0Q
1P
0Z
0Y
1X
x0
x/
x.
x-
x,
x+
x*
x)
#370
0!
#375
1!
1R
00
0/
0.
0-
0,
0+
0*
0)
1Z
x0
x/
x.
x-
x,
x+
x*
x)
#380
0!
#385
1!
00
0/
0.
0-
0,
0+
0*
0)
0R
1Q
0Z
1Y
x0
x/
x.
x-
x,
x+
x*
x)
#390
0!
#395
1!
1R
00
0/
0.
0-
0,
0+
0*
0)
1Z
x0
x/
x.
x-
x,
x+
x*
x)
#400
0!
#405
1!
00
0/
0.
0-
0,
0+
0*
0)
0R
0Q
0P
0O
0N
1M
0Z
0Y
0X
0W
0V
1U
x0
x/
x.
x-
x,
x+
x*
x)
#410
0!
#415
1!
1R
00
0/
0.
0-
0,
0+
0*
0)
1Z
x0
x/
x.
x-
x,
x+
x*
x)
#420
0!
#425
1!
00
0/
0.
0-
0,
0+
0*
0)
0R
1Q
0Z
1Y
x0
x/
x.
x-
x,
x+
x*
x)
#430
0!
#435
1!
1R
00
0/
0.
0-
0,
0+
0*
0)
1Z
x0
x/
x.
x-
x,
x+
x*
x)
#440
0!
#445
1!
00
0/
0.
0-
0,
0+
0*
0)
0R
0Q
1P
0Z
0Y
1X
x0
x/
x.
x-
x,
x+
x*
x)
#450
0!
#455
1!
1R
00
0/
0.
0-
0,
0+
0*
0)
1Z
x0
x/
x.
x-
x,
x+
x*
x)
#460
0!
#465
1!
00
0/
0.
0-
0,
0+
0*
0)
0R
1Q
0Z
1Y
x0
x/
x.
x-
x,
x+
x*
x)
#470
0!
#475
1!
1R
00
0/
0.
0-
0,
0+
0*
0)
1Z
x0
x/
x.
x-
x,
x+
x*
x)
#480
0!
#485
1!
00
0/
0.
0-
0,
0+
0*
0)
0R
0Q
0P
1O
0Z
0Y
0X
1W
x0
x/
x.
x-
x,
x+
x*
x)
#490
0!
#495
1!
1R
00
0/
0.
0-
0,
0+
0*
0)
1Z
x0
x/
x.
x-
x,
x+
x*
x)
#500
0!
#505
1!
00
0/
0.
0-
0,
0+
0*
0)
0R
1Q
0Z
1Y
x0
x/
x.
x-
x,
x+
x*
x)
#510
0!
#515
1!
1R
00
0/
0.
0-
0,
0+
0*
0)
1Z
x0
x/
x.
x-
x,
x+
x*
x)
#520
0!
#525
1!
00
0/
0.
0-
0,
0+
0*
0)
0R
0Q
1P
0Z
0Y
1X
x0
x/
x.
x-
x,
x+
x*
x)
#530
0!
#535
1!
1R
00
0/
0.
0-
0,
0+
0*
0)
1Z
x0
x/
x.
x-
x,
x+
x*
x)
#540
0!
#545
1!
00
0/
0.
0-
0,
0+
0*
0)
0R
1Q
0Z
1Y
x0
x/
x.
x-
x,
x+
x*
x)
#550
0!
#555
1!
1R
00
0/
0.
0-
0,
0+
0*
0)
1Z
x0
x/
x.
x-
x,
x+
x*
x)
#560
0!
#565
1!
00
0/
0.
0-
0,
0+
0*
0)
0R
0Q
0P
0O
1N
0Z
0Y
0X
0W
1V
x0
x/
x.
x-
x,
x+
x*
x)
#570
0!
#575
1!
1R
00
0/
0.
0-
0,
0+
0*
0)
1Z
x0
x/
x.
x-
x,
x+
x*
x)
#580
0!
#585
1!
00
0/
0.
0-
0,
0+
0*
0)
0R
1Q
0Z
1Y
x0
x/
x.
x-
x,
x+
x*
x)
#590
0!
#595
1!
1R
00
0/
0.
0-
0,
0+
0*
0)
1Z
x0
x/
x.
x-
x,
x+
x*
x)
#600
0!
#605
1!
00
0/
0.
0-
0,
0+
0*
0)
0R
0Q
1P
0Z
0Y
1X
x0
x/
x.
x-
x,
x+
x*
x)
#610
0!
#615
1!
1R
00
0/
0.
0-
0,
0+
0*
0)
1Z
x0
x/
x.
x-
x,
x+
x*
x)
#620
0!
#625
1!
00
0/
0.
0-
0,
0+
0*
0)
0R
1Q
0Z
1Y
x0
x/
x.
x-
x,
x+
x*
x)
#630
0!
#635
1!
1R
00
0/
0.
0-
0,
0+
0*
0)
1Z
x0
x/
x.
x-
x,
x+
x*
x)
#640
0!
#645
1!
00
0/
0.
0-
0,
0+
0*
0)
0R
0Q
0P
1O
0Z
0Y
0X
1W
x0
x/
x.
x-
x,
x+
x*
x)
#650
0!
#655
1!
1R
00
0/
0.
0-
0,
0+
0*
0)
1Z
x0
x/
x.
x-
x,
x+
x*
x)
#660
0!
#665
1!
00
0/
0.
0-
0,
0+
0*
0)
0R
1Q
0Z
1Y
x0
x/
x.
x-
x,
x+
x*
x)
#670
0!
#675
1!
1R
00
0/
0.
0-
0,
0+
0*
0)
1Z
x0
x/
x.
x-
x,
x+
x*
x)
#680
0!
#685
1!
00
0/
0.
0-
0,
0+
0*
0)
0R
0Q
1P
0Z
0Y
1X
x0
x/
x.
x-
x,
x+
x*
x)
#690
0!
#695
1!
1R
00
0/
0.
0-
0,
0+
0*
0)
1Z
x0
x/
x.
x-
x,
x+
x*
x)
#700
0!
#705
1!
00
0/
0.
0-
0,
0+
0*
0)
0R
1Q
0Z
1Y
x0
x/
x.
x-
x,
x+
x*
x)
#710
0!
#715
1!
1R
00
0/
0.
0-
0,
0+
0*
0)
1Z
x0
x/
x.
x-
x,
x+
x*
x)
#720
0!
#725
1!
00
0/
0.
0-
0,
0+
0*
0)
0R
0Q
0P
0O
0N
0M
1L
0Z
0Y
0X
0W
0V
0U
1T
x0
x/
x.
x-
x,
x+
x*
x)
#730
0!
#735
1!
1R
00
0/
0.
0-
0,
0+
0*
0)
1Z
x0
x/
x.
x-
x,
x+
x*
x)
#740
0!
#745
1!
00
0/
0.
0-
0,
0+
0*
0)
0R
1Q
0Z
1Y
x0
x/
x.
x-
x,
x+
x*
x)
#750
0!
#755
1!
1R
00
0/
0.
0-
0,
0+
0*
0)
1Z
x0
x/
x.
x-
x,
x+
x*
x)
#760
0!
#765
1!
00
0/
0.
0-
0,
0+
0*
0)
0R
0Q
1P
0Z
0Y
1X
x0
x/
x.
x-
x,
x+
x*
x)
#770
0!
#775
1!
1R
00
0/
0.
0-
0,
0+
0*
0)
1Z
x0
x/
x.
x-
x,
x+
x*
x)
#780
0!
#785
1!
00
0/
0.
0-
0,
0+
0*
0)
0R
1Q
0Z
1Y
x0
x/
x.
x-
x,
x+
x*
x)
#790
0!
#795
1!
1R
00
0/
0.
0-
0,
0+
0*
0)
1Z
x0
x/
x.
x-
x,
x+
x*
x)
#800
0!
#805
1!
00
0/
0.
0-
0,
0+
0*
0)
0R
0Q
0P
1O
0Z
0Y
0X
1W
x0
x/
x.
x-
x,
x+
x*
x)
#810
0!
#815
1!
1R
00
0/
0.
0-
0,
0+
0*
0)
1Z
x0
x/
x.
x-
x,
x+
x*
x)
#820
0!
#825
1!
00
0/
0.
0-
0,
0+
0*
0)
0R
1Q
0Z
1Y
x0
x/
x.
x-
x,
x+
x*
x)
#830
0!
#835
1!
1R
00
0/
0.
0-
0,
0+
0*
0)
1Z
x0
x/
x.
x-
x,
x+
x*
x)
#840
0!
#845
1!
00
0/
0.
0-
0,
0+
0*
0)
0R
0Q
1P
0Z
0Y
1X
x0
x/
x.
x-
x,
x+
x*
x)
#850
0!
#855
1!
1R
00
0/
0.
0-
0,
0+
0*
0)
1Z
x0
x/
x.
x-
x,
x+
x*
x)
#860
0!
#865
1!
00
0/
0.
0-
0,
0+
0*
0)
0R
1Q
0Z
1Y
x0
x/
x.
x-
x,
x+
x*
x)
#870
0!
#875
1!
1R
00
0/
0.
0-
0,
0+
0*
0)
1Z
x0
x/
x.
x-
x,
x+
x*
x)
#880
0!
#885
1!
00
0/
0.
0-
0,
0+
0*
0)
0R
0Q
0P
0O
1N
0Z
0Y
0X
0W
1V
x0
x/
x.
x-
x,
x+
x*
x)
#890
0!
#895
1!
1R
00
0/
0.
0-
0,
0+
0*
0)
1Z
x0
x/
x.
x-
x,
x+
x*
x)
#900
0!
#905
1!
00
0/
0.
0-
0,
0+
0*
0)
0R
1Q
0Z
1Y
x0
x/
x.
x-
x,
x+
x*
x)
#910
0!
#915
1!
1R
00
0/
0.
0-
0,
0+
0*
0)
1Z
x0
x/
x.
x-
x,
x+
x*
x)
#920
0!
#925
1!
00
0/
0.
0-
0,
0+
0*
0)
0R
0Q
1P
0Z
0Y
1X
x0
x/
x.
x-
x,
x+
x*
x)
#930
0!
#935
1!
1R
00
0/
0.
0-
0,
0+
0*
0)
1Z
x0
x/
x.
x-
x,
x+
x*
x)
#940
0!
#945
1!
00
0/
0.
0-
0,
0+
0*
0)
0R
1Q
0Z
1Y
x0
x/
x.
x-
x,
x+
x*
x)
#950
0!
#955
1!
1R
00
0/
0.
0-
0,
0+
0*
0)
1Z
x0
x/
x.
x-
x,
x+
x*
x)
#960
0!
#965
1!
00
0/
0.
0-
0,
0+
0*
0)
0R
0Q
0P
1O
0Z
0Y
0X
1W
x0
x/
x.
x-
x,
x+
x*
x)
#970
0!
#975
1!
1R
00
0/
0.
0-
0,
0+
0*
0)
1Z
x0
x/
x.
x-
x,
x+
x*
x)
#980
0!
#985
1!
00
0/
0.
0-
0,
0+
0*
0)
0R
1Q
0Z
1Y
x0
x/
x.
x-
x,
x+
x*
x)
#990
0!
#995
1!
1R
00
0/
0.
0-
0,
0+
0*
0)
1Z
x0
x/
x.
x-
x,
x+
x*
x)
#1000
0!
#1005
1!
00
0/
0.
0-
0,
0+
0*
0)
0R
0Q
1P
0Z
0Y
1X
x0
x/
x.
x-
x,
x+
x*
x)
#1010
0!
#1015
1!
1R
00
0/
0.
0-
0,
0+
0*
0)
1Z
x0
x/
x.
x-
x,
x+
x*
x)
#1020
0!
#1025
1!
00
0/
0.
0-
0,
0+
0*
0)
0R
1Q
0Z
1Y
x0
x/
x.
x-
x,
x+
x*
x)
#1030
0!
#1035
1!
1R
00
0/
0.
0-
0,
0+
0*
0)
1Z
x0
x/
x.
x-
x,
x+
x*
x)
#1040
0!
#1045
1!
00
0/
0.
0-
0,
0+
0*
0)
0R
0Q
0P
0O
0N
1M
0Z
0Y
0X
0W
0V
1U
x0
x/
x.
x-
x,
x+
x*
x)
#1050
0!
#1055
1!
1R
00
0/
0.
0-
0,
0+
0*
0)
1Z
x0
x/
x.
x-
x,
x+
x*
x)
#1060
0!
#1065
1!
00
0/
0.
0-
0,
0+
0*
0)
0R
1Q
0Z
1Y
x0
x/
x.
x-
x,
x+
x*
x)
#1070
0!
#1075
1!
1R
00
0/
0.
0-
0,
0+
0*
0)
1Z
x0
x/
x.
x-
x,
x+
x*
x)
#1080
0!
#1085
1!
00
0/
0.
0-
0,
0+
0*
0)
0R
0Q
1P
0Z
0Y
1X
x0
x/
x.
x-
x,
x+
x*
x)
#1090
0!
#1095
1!
1R
00
0/
0.
0-
0,
0+
0*
0)
1Z
x0
x/
x.
x-
x,
x+
x*
x)
#1100
0!
#1105
1!
00
0/
0.
0-
0,
0+
0*
0)
0R
1Q
0Z
1Y
x0
x/
x.
x-
x,
x+
x*
x)
#1110
0!
#1115
1!
1R
00
0/
0.
0-
0,
0+
0*
0)
1Z
x0
x/
x.
x-
x,
x+
x*
x)
#1120
0!
#1125
1!
00
0/
0.
0-
0,
0+
0*
0)
0R
0Q
0P
1O
0Z
0Y
0X
1W
x0
x/
x.
x-
x,
x+
x*
x)
#1130
0!
#1135
1!
1R
00
0/
0.
0-
0,
0+
0*
0)
1Z
x0
x/
x.
x-
x,
x+
x*
x)
#1140
0!
#1145
1!
00
0/
0.
0-
0,
0+
0*
0)
0R
1Q
0Z
1Y
x0
x/
x.
x-
x,
x+
x*
x)
#1150
0!
#1155
1!
1R
00
0/
0.
0-
0,
0+
0*
0)
1Z
x0
x/
x.
x-
x,
x+
x*
x)
#1160
0!
#1165
1!
00
0/
0.
0-
0,
0+
0*
0)
0R
0Q
1P
0Z
0Y
1X
x0
x/
x.
x-
x,
x+
x*
x)
#1170
0!
