timing_gotchas/timing_gotchas.sv
timeunit 1ps;
timeprecision 1ps;

// Min-delay gotcha: a launch flop feeds a capture flop through a path whose
// contamination delay is shorter than the capture flop hold requirement.
module MinDelayHoldDemo #(
  parameter int CONTAM_DELAY_PS = 20,
  parameter int HOLD_REQ_PS     = 80
) (
  input  logic clk,
  input  logic rst_n,
  input  logic launch_d,
  output logic launch_q,
  output wire  capture_d,
  output logic capture_q,
  output logic hold_window,
  output logic hold_violation,
  output logic hold_violation_pulse
);
  initial begin
    launch_q             = 1'b0;
    capture_q            = 1'b0;
    hold_window          = 1'b0;
    hold_violation       = 1'b0;
    hold_violation_pulse = 1'b0;
  end

  assign #(CONTAM_DELAY_PS) capture_d = launch_q;

  always @(posedge clk or negedge rst_n) begin
    if (!rst_n) begin
      launch_q    <= 1'b0;
      capture_q   <= 1'b0;
      hold_window <= 1'b0;
    end else begin
      launch_q    <= launch_d;
      capture_q   <= capture_d;
      hold_window <= 1'b1;
      fork
        begin
          #(HOLD_REQ_PS) hold_window <= 1'b0;
        end
      join_none
    end
  end

  always @(capture_d or negedge rst_n) begin
    if (!rst_n) begin
      hold_violation       <= 1'b0;
      hold_violation_pulse <= 1'b0;
    end else if (hold_window) begin
      hold_violation       <= 1'b1;
      hold_violation_pulse <= 1'b1;
      fork
        begin
          #1 hold_violation_pulse <= 1'b0;
        end
      join_none
    end
  end
endmodule

// Max-delay gotcha: a launch flop feeds a capture flop through a path whose
// propagation delay leaves less than SETUP_REQ_PS before the next clock edge.
module MaxDelaySetupDemo #(
  parameter int PROP_DELAY_PS   = 920,
  parameter int SETUP_REQ_PS    = 150,
  parameter int CLOCK_PERIOD_PS = 1000
) (
  input  logic clk,
  input  logic rst_n,
  input  logic launch_d,
  output logic launch_q,
  output wire  capture_d,
  output logic capture_q,
  output logic setup_window,
  output logic setup_violation,
  output logic setup_violation_pulse
);
  initial begin
    launch_q              = 1'b0;
    capture_q             = 1'b0;
    setup_window          = 1'b0;
    setup_violation       = 1'b0;
    setup_violation_pulse = 1'b0;
  end

  assign #(PROP_DELAY_PS) capture_d = launch_q;

  always @(posedge clk or negedge rst_n) begin
    if (!rst_n) begin
      launch_q     <= 1'b0;
      capture_q    <= 1'b0;
      setup_window <= 1'b0;
    end else begin
      launch_q     <= launch_d;
      capture_q    <= capture_d;
      setup_window <= 1'b0;
      fork
        begin
          #(CLOCK_PERIOD_PS - SETUP_REQ_PS) setup_window <= 1'b1;
          #(SETUP_REQ_PS) setup_window <= 1'b0;
        end
      join_none
    end
  end

  always @(capture_d or negedge rst_n) begin
    if (!rst_n) begin
      setup_violation       <= 1'b0;
      setup_violation_pulse <= 1'b0;
    end else if (setup_window) begin
      setup_violation       <= 1'b1;
      setup_violation_pulse <= 1'b1;
      fork
        begin
          #1 setup_violation_pulse <= 1'b0;
        end
      join_none
    end
  end
endmodule

timing_gotchas/timing_gotchas_tb.sv
`ifndef VCD_FILE
`define VCD_FILE "timing_gotchas_waveforms.vcd"
`endif

timeunit 1ps;
timeprecision 1ps;

module top;
  localparam int CLOCK_PERIOD_PS = 1000;
  localparam int HOLD_REQ_PS     = 80;
  localparam int SETUP_REQ_PS    = 150;

  logic clk;
  logic rst_n;
  logic launch_d;

  wire min_fast_launch_q;
  wire min_fast_capture_d;
  wire min_fast_capture_q;
  wire min_fast_hold_window;
  wire min_fast_hold_violation;
  wire min_fast_hold_violation_pulse;

  wire min_padded_launch_q;
  wire min_padded_capture_d;
  wire min_padded_capture_q;
  wire min_padded_hold_window;
  wire min_padded_hold_violation;
  wire min_padded_hold_violation_pulse;

  wire max_slow_launch_q;
  wire max_slow_capture_d;
  wire max_slow_capture_q;
  wire max_slow_setup_window;
  wire max_slow_setup_violation;
  wire max_slow_setup_violation_pulse;

  wire max_ok_launch_q;
  wire max_ok_capture_d;
  wire max_ok_capture_q;
  wire max_ok_setup_window;
  wire max_ok_setup_violation;
  wire max_ok_setup_violation_pulse;

  integer min_gotcha_count;
  integer max_gotcha_count;
  integer clean_count;
  integer errors;

  MinDelayHoldDemo #(
    .CONTAM_DELAY_PS(20),
    .HOLD_REQ_PS(HOLD_REQ_PS)
  ) min_fast (
    .clk(clk),
    .rst_n(rst_n),
    .launch_d(launch_d),
    .launch_q(min_fast_launch_q),
    .capture_d(min_fast_capture_d),
    .capture_q(min_fast_capture_q),
    .hold_window(min_fast_hold_window),
    .hold_violation(min_fast_hold_violation),
    .hold_violation_pulse(min_fast_hold_violation_pulse)
  );

  MinDelayHoldDemo #(
    .CONTAM_DELAY_PS(120),
    .HOLD_REQ_PS(HOLD_REQ_PS)
  ) min_padded (
    .clk(clk),
    .rst_n(rst_n),
    .launch_d(launch_d),
    .launch_q(min_padded_launch_q),
    .capture_d(min_padded_capture_d),
    .capture_q(min_padded_capture_q),
    .hold_window(min_padded_hold_window),
    .hold_violation(min_padded_hold_violation),
    .hold_violation_pulse(min_padded_hold_violation_pulse)
  );

  MaxDelaySetupDemo #(
    .PROP_DELAY_PS(920),
    .SETUP_REQ_PS(SETUP_REQ_PS),
    .CLOCK_PERIOD_PS(CLOCK_PERIOD_PS)
  ) max_slow (
    .clk(clk),
    .rst_n(rst_n),
    .launch_d(launch_d),
    .launch_q(max_slow_launch_q),
    .capture_d(max_slow_capture_d),
    .capture_q(max_slow_capture_q),
    .setup_window(max_slow_setup_window),
    .setup_violation(max_slow_setup_violation),
    .setup_violation_pulse(max_slow_setup_violation_pulse)
  );

  MaxDelaySetupDemo #(
    .PROP_DELAY_PS(700),
    .SETUP_REQ_PS(SETUP_REQ_PS),
    .CLOCK_PERIOD_PS(CLOCK_PERIOD_PS)
  ) max_ok (
    .clk(clk),
    .rst_n(rst_n),
    .launch_d(launch_d),
    .launch_q(max_ok_launch_q),
    .capture_d(max_ok_capture_d),
    .capture_q(max_ok_capture_q),
    .setup_window(max_ok_setup_window),
    .setup_violation(max_ok_setup_violation),
    .setup_violation_pulse(max_ok_setup_violation_pulse)
  );

  initial begin
    $dumpfile(`VCD_FILE);
    $dumpvars(0);
  end

  initial begin
    clk = 1'b0;
    forever #(CLOCK_PERIOD_PS / 2) clk = ~clk;
  end

  always @(posedge min_fast_hold_violation_pulse) begin
    min_gotcha_count = min_gotcha_count + 1;
    $display("GOTCHA OBSERVED min-delay/hold: t=%0t ps path=20 ps hold=%0d ps",
             $time, HOLD_REQ_PS);
  end

  always @(posedge max_slow_setup_violation_pulse) begin
    max_gotcha_count = max_gotcha_count + 1;
    $display("GOTCHA OBSERVED max-delay/setup: t=%0t ps path=920 ps setup=%0d ps",
             $time, SETUP_REQ_PS);
  end

  always @(posedge min_padded_hold_violation_pulse) begin
    errors = errors + 1;
    $display("*** FIX FAILED: padded min-delay path reported hold violation at t=%0t ps", $time);
  end

  always @(posedge max_ok_setup_violation_pulse) begin
    errors = errors + 1;
    $display("*** FIX FAILED: max-delay clean path reported setup violation at t=%0t ps", $time);
  end

  task automatic drive_one_cycle(input logic value);
    begin
      @(negedge clk);
      #100;
      launch_d = value;
    end
  endtask

  initial begin
    min_gotcha_count = 0;
    max_gotcha_count = 0;
    clean_count      = 0;
    errors           = 0;
    rst_n            = 1'b0;
    launch_d         = 1'b0;

    $display("time(ps)  launch_d  min_fast_d  min_padded_d  max_slow_d  max_ok_d");
    #200;
    rst_n = 1'b1;

    drive_one_cycle(1'b1);
    drive_one_cycle(1'b0);
    drive_one_cycle(1'b1);
    drive_one_cycle(1'b0);

    #(CLOCK_PERIOD_PS * 2);

    if (min_gotcha_count == 0) begin
      errors = errors + 1;
      $display("*** Error: min-delay/hold gotcha never triggered");
    end
    if (max_gotcha_count == 0) begin
      errors = errors + 1;
      $display("*** Error: max-delay/setup gotcha never triggered");
    end
    if (!min_padded_hold_violation) clean_count = clean_count + 1;
    else begin
      errors = errors + 1;
      $display("*** Error: padded min-delay path latched a hold violation");
    end
    if (!max_ok_setup_violation) clean_count = clean_count + 1;
    else begin
      errors = errors + 1;
      $display("*** Error: clean max-delay path latched a setup violation");
    end

    if (errors == 0)
      $display("No errors -- passed testbench  (gotcha caught min=%0d max=%0d, clean paths %0d/2)",
               min_gotcha_count, max_gotcha_count, clean_count);
    else
      $display("*** Error: timing gotcha testbench found %0d errors", errors);

    $finish;
  end
endmodule

timing_gotchas/timing_gotchas_waveforms.vcd
$date
	Mon May 25 21:38:21 2026
$end
$version
	QuestaSim Version 2021.3_1
$end
$timescale
	1ps
$end

$scope module top $end
$var parameter 32 ! CLOCK_PERIOD_PS $end
$var parameter 32 " HOLD_REQ_PS $end
$var parameter 32 # SETUP_REQ_PS $end
$var reg 1 $ clk $end
$var reg 1 % rst_n $end
$var reg 1 & launch_d $end
$var wire 1 ' min_fast_launch_q $end
$var wire 1 ( min_fast_capture_d $end
$var wire 1 ) min_fast_capture_q $end
$var wire 1 * min_fast_hold_window $end
$var wire 1 + min_fast_hold_violation $end
$var wire 1 , min_fast_hold_violation_pulse $end
$var wire 1 - min_padded_launch_q $end
$var wire 1 . min_padded_capture_d $end
$var wire 1 / min_padded_capture_q $end
$var wire 1 0 min_padded_hold_window $end
$var wire 1 1 min_padded_hold_violation $end
$var wire 1 2 min_padded_hold_violation_pulse $end
$var wire 1 3 max_slow_launch_q $end
$var wire 1 4 max_slow_capture_d $end
$var wire 1 5 max_slow_capture_q $end
$var wire 1 6 max_slow_setup_window $end
$var wire 1 7 max_slow_setup_violation $end
$var wire 1 8 max_slow_setup_violation_pulse $end
$var wire 1 9 max_ok_launch_q $end
$var wire 1 : max_ok_capture_d $end
$var wire 1 ; max_ok_capture_q $end
$var wire 1 < max_ok_setup_window $end
$var wire 1 = max_ok_setup_violation $end
$var wire 1 > max_ok_setup_violation_pulse $end
$var integer 32 ? min_gotcha_count $end
$var integer 32 @ max_gotcha_count $end
$var integer 32 A clean_count $end
$var integer 32 B errors $end

$scope task drive_one_cycle $end
$upscope $end

$scope module min_fast $end
$var parameter 32 C CONTAM_DELAY_PS $end
$var parameter 32 D HOLD_REQ_PS $end
$var wire 1 E clk $end
$var wire 1 F rst_n $end
$var wire 1 G launch_d $end
$var reg 1 H launch_q $end
$var wire 1 ( capture_d $end
$var reg 1 I capture_q $end
$var reg 1 J hold_window $end
$var reg 1 K hold_violation $end
$var reg 1 L hold_violation_pulse $end
$upscope $end

$scope module min_padded $end
$var parameter 32 M CONTAM_DELAY_PS $end
$var parameter 32 N HOLD_REQ_PS $end
$var wire 1 O clk $end
$var wire 1 P rst_n $end
$var wire 1 Q launch_d $end
$var reg 1 R launch_q $end
$var wire 1 . capture_d $end
$var reg 1 S capture_q $end
$var reg 1 T hold_window $end
$var reg 1 U hold_violation $end
$var reg 1 V hold_violation_pulse $end
$upscope $end

$scope module max_slow $end
$var parameter 32 W PROP_DELAY_PS $end
$var parameter 32 X SETUP_REQ_PS $end
$var parameter 32 Y CLOCK_PERIOD_PS $end
$var wire 1 Z clk $end
$var wire 1 [ rst_n $end
$var wire 1 \ launch_d $end
$var reg 1 ] launch_q $end
$var wire 1 4 capture_d $end
$var reg 1 ^ capture_q $end
$var reg 1 _ setup_window $end
$var reg 1 ` setup_violation $end
$var reg 1 a setup_violation_pulse $end
$upscope $end

$scope module max_ok $end
$var parameter 32 b PROP_DELAY_PS $end
$var parameter 32 c SETUP_REQ_PS $end
$var parameter 32 d CLOCK_PERIOD_PS $end
$var wire 1 e clk $end
$var wire 1 f rst_n $end
$var wire 1 g launch_d $end
$var reg 1 h launch_q $end
$var wire 1 : capture_d $end
$var reg 1 i capture_q $end
$var reg 1 j setup_window $end
$var reg 1 k setup_violation $end
$var reg 1 l setup_violation_pulse $end
$upscope $end
$upscope $end
$enddefinitions $end
#0
$dumpvars
0$
0%
0&
0H
0I
0J
0K
0L
0R
0S
0T
0U
0V
0]
0^
0_
0`
0a
0h
0i
0j
0k
0l
b1111101000 !
b1010000 "
b10010110 #
b10100 C
b1010000 D
b1111000 M
b1010000 N
b1110011000 W
b10010110 X
b1111101000 Y
b1010111100 b
b10010110 c
b1111101000 d
b0 ?
b0 @
b0 A
b0 B
0'
x(
0)
0*
0+
0,
0-
x.
0/
00
01
02
03
x4
05
06
07
08
09
x:
0;
0<
0=
0>
0g
0f
0e
0\
0[
0Z
0Q
0P
0O
0G
0F
0E
$end
#20
0(
#120
0.
#200
1%
1F
1P
1[
1f
#500
1$
1E
1O
1Z
1e
xi
x^
1T
1J
x;
x5
10
1*
#580
0T
0J
00
0*
#700
0:
#920
04
#1000
0$
0E
0O
0Z
0e
#1100
1&
1G
1Q
1\
1g
#1350
1j
1_
1<
16
#1500
1$
1E
1O
1Z
1e
0j
0_
1h
0i
1]
0^
1R
1T
1H
1J
0<
06
19
0;
13
05
1-
10
1'
1*
#1520
1(
1K
1L
1+
1,
b1 ?
#1521
0L
0,
#1580
0T
0J
00
0*
#1620
1.
#2000
0$
0E
0O
0Z
0e
#2100
0&
0G
0Q
0\
0g
#2200
1:
#2350
1j
1_
1<
16
#2420
14
1`
1a
17
18
b1 @
#2421
0a
08
#2500
1$
1E
1O
1Z
1e
0j
0_
0h
1i
0]
1^
0R
1S
1T
0H
1I
1J
0<
06
09
1;
03
15
0-
1/
10
0'
1)
1*
#2520
0(
1L
1,
b10 ?
#2521
0L
0,
#2580
0T
0J
00
0*
#2620
0.
#3000
0$
0E
0O
0Z
0e
#3100
1&
1G
1Q
1\
1g
#3200
0:
#3350
1j
1_
1<
16
#3420
04
1a
18
b10 @
#3421
0a
08
#3500
1$
1E
1O
1Z
1e
0j
0_
1h
0i
1]
0^
1R
0S
1T
1H
0I
1J
0<
06
19
0;
13
05
1-
0/
10
1'
0)
1*
#3520
1(
1L
1,
b11 ?
#3521
0L
0,
#3580
0T
0J
00
0*
#3620
1.
#4000
0$
0E
0O
0Z
0e
#4100
0&
0G
0Q
0\
0g
#4200
1:
#4350
1j
1_
1<
16
#4420
14
1a
18
b11 @
#4421
0a
08
#4500
1$
1E
1O
1Z
1e
0j
0_
0h
1i
0]
1^
0R
1S
1T
0H
1I
1J
0<
06
09
1;
03
15
0-
1/
10
0'
1)
1*
#4520
0(
1L
1,
b100 ?
#4521
0L
0,
#4580
0T
0J
00
0*
#4620
0.
#5000
0$
0E
0O
0Z
0e
#5200
0:
#5350
1j
1_
1<
16
#5420
04
1a
18
b100 @
#5421
0a
08
#5500
1$
1E
1O
1Z
1e
0j
0_
0i
0^
0S
1T
0I
1J
0<
06
0;
05
0/
10
0)
1*
#5580
0T
0J
00
0*
#6000
0$
0E
0O
0Z
0e
#6100
b1 A
b10 A
